MANIFEST.in
README.md
setup.py
bin/get_names.bat
get_names/__init__.py
get_names/get_names.py
my_cool_lib.egg-info/PKG-INFO
my_cool_lib.egg-info/SOURCES.txt
my_cool_lib.egg-info/dependency_links.txt
my_cool_lib.egg-info/requires.txt
my_cool_lib.egg-info/top_level.txt