Metadata-Version: 1.0
Name: my-cool-lib
Version: 0.1.0
Summary: Super useful library
Home-page: https://github.com
Author: SomeCompany PLC
Author-email: dev@example.com
License: UNKNOWN
Platform: UNKNOWN
